README.md
setup.py
tap_platformpurple/__init__.py
tap_platformpurple/client.py
tap_platformpurple.egg-info/PKG-INFO
tap_platformpurple.egg-info/SOURCES.txt
tap_platformpurple.egg-info/dependency_links.txt
tap_platformpurple.egg-info/entry_points.txt
tap_platformpurple.egg-info/requires.txt
tap_platformpurple.egg-info/top_level.txt
tap_platformpurple/schemas/events.json
tap_platformpurple/schemas/products.json
tap_platformpurple/schemas/transactions.json
tap_platformpurple/schemas/user_access.json
tap_platformpurple/schemas/user_info.json
tap_platformpurple/schemas/user_referrals.json
tap_platformpurple/streams/__init__.py
tap_platformpurple/streams/base.py
tap_platformpurple/streams/events.py
tap_platformpurple/streams/products.py
tap_platformpurple/streams/transactions.py
tap_platformpurple/streams/user_access.py
tap_platformpurple/streams/user_info.py
tap_platformpurple/streams/user_referrals.py