Metadata-Version: 1.1
Name: tap-platformpurple
Version: 1.1.0
Summary: Singer.io tap for extracting data from the Platform Purple API
Home-page: http://fishtownanalytics.com
Author: Fishtown Analytics
Author-email: UNKNOWN
License: UNKNOWN
Platform: UNKNOWN
Classifier: Programming Language :: Python :: 3 :: Only
